finance_quote_python/__init__.py
finance_quote_python/alphavantage.py
finance_quote_python/boerse_frankfurt.py
finance_quote_python/boerse_frankfurt_old.py
finance_quote_python/finance.py
finance_quote_python/fixerio.py
finance_quote_python/morningstar.py
finance_quote_python/morningstar_de.py
finance_quote_python/morningstar_json.py
finance_quote_python/nordnet.py
finance_quote_python/reuters.py
finance_quote_python/vanguard_au.py
finance_quote_python/yahoo_finance.py
finance_quote_python/yahoo_finance_web.py
finance_quote_python-1.8.7.dist-info/LICENSE
finance_quote_python-1.8.7.dist-info/METADATA
finance_quote_python-1.8.7.dist-info/WHEEL
finance_quote_python-1.8.7.dist-info/top_level.txt
finance_quote_python-1.8.7.dist-info/RECORD
