Metadata-Version: 2.1
Name: finance-quote-python
Version: 1.8.7
Summary: Finance::Quote implementation in Python
Home-page: https://gitlab.com/alensiljak/finance-quote-python
Author: Alen Siljak
License: GPL3
Platform: UNKNOWN
License-File: LICENSE
Requires-Dist: requests
